pyswahili/__init__.py
pyswahili/__main__.py
pyswahili/repl.py
pyswahili/sw_to_en.py
pyswahili/swahili_node.py
pyswahili-0.1.4.dist-info/LICENSE
pyswahili-0.1.4.dist-info/METADATA
pyswahili-0.1.4.dist-info/WHEEL
pyswahili-0.1.4.dist-info/entry_points.txt
pyswahili-0.1.4.dist-info/top_level.txt
pyswahili-0.1.4.dist-info/RECORD
