Metadata-Version: 2.1
Name: pyswahili
Version: 0.1.4
Summary: 
Home-page: https://github.com/Kalebu/pyswahili
Author: Jordan Kalebu
Author-email: isaackeinstein@gmail.com
License: MIT
Download-URL: https://github.com/Kalebu/pyswahili/releases/tag/0.1
Keywords: pyswahili,python-tanzania,python-transpiler,swahili-python,python in swahili,python for swahili speakers,code python in swahili,swahili programming language,program in swahili
Platform: UNKNOWN
Classifier: Development Status :: 3 - Alpha
Classifier: Intended Audience :: Developers
Classifier: Topic :: Software Development :: Build Tools
Classifier: License :: OSI Approved :: MIT License
Classifier: Programming Language :: Python :: 3.6
Classifier: Programming Language :: Python :: 3.7
Classifier: Programming Language :: Python :: 3.8
Classifier: Programming Language :: Python :: 3.9
